dataeyes_mcp-0.1.0.dist-info/licenses/LICENSE
dataeyes_mcp_server/__init__.py
dataeyes_mcp_server/__main__.py
dataeyes_mcp_server/dataeyes.py
dataeyes_mcp-0.1.0.dist-info/METADATA
dataeyes_mcp-0.1.0.dist-info/WHEEL
dataeyes_mcp-0.1.0.dist-info/entry_points.txt
dataeyes_mcp-0.1.0.dist-info/top_level.txt
dataeyes_mcp-0.1.0.dist-info/RECORD
