Metadata-Version: 2.4
Name: dataeyes-mcp
Version: 0.1.0
Summary: Dataeyes MCP Server
Keywords: http,mcp,dataeyes
Requires-Python: >=3.13
License-File: LICENSE
Requires-Dist: httpx>=0.28.1
Requires-Dist: mcp[cli]>=1.9.4
Dynamic: license-file
